hog/__init__.py
hog/__main__.py
hog/const.py
hog/hog.py
hog/wrapped.py
hog/utils/__init__.py
hog/utils/args.py
hog/utils/get_filenames.py
hog/utils/get_logcategory.py
hog/utils/print_logs.py
hog/utils/verify_selected_logfiles.py
tests/__init__.py
tests/data.py
tests/test_does_name_match_pattern.py
tests/test_get_logcategory.py
tests/test_get_word_list_without_matching_word.py
tests/test_select_filenames.py
tests/test_wrapped.py
scribehog-1.4.3.dist-info/LICENSE
scribehog-1.4.3.dist-info/METADATA
scribehog-1.4.3.dist-info/WHEEL
scribehog-1.4.3.dist-info/entry_points.txt
scribehog-1.4.3.dist-info/top_level.txt
scribehog-1.4.3.dist-info/RECORD
