Metadata-Version: 2.1
Name: scribehog
Version: 1.4.3
Summary: Log digging helper
Home-page: https://github.com/endreymarcell/hog
Author: Marcell Endrey
Author-email: endrey.marcell@gmail.com
License: UNKNOWN
Platform: UNKNOWN
Classifier: Programming Language :: Python :: 3
Classifier: License :: OSI Approved :: MIT License
Classifier: Operating System :: OS Independent
